asl/__init__.py
asl/asl.py
asl/timelapse.py
asl_screenlapse-0.1.3.dist-info/LICENSE
asl_screenlapse-0.1.3.dist-info/METADATA
asl_screenlapse-0.1.3.dist-info/WHEEL
asl_screenlapse-0.1.3.dist-info/entry_points.txt
asl_screenlapse-0.1.3.dist-info/top_level.txt
asl_screenlapse-0.1.3.dist-info/RECORD
