Metadata-Version: 2.1
Name: asl-screenlapse
Version: 0.1.3
Summary: a resource-inexpensive way to create timelapses from your screen
Home-page: https://github.com/skuzzymiglet/asl
Author: skuzzymiglet
Author-email: skuzzymiglet@gmail.com
License: UNKNOWN
Platform: UNKNOWN
Classifier: Programming Language :: Python :: 3
Classifier: License :: OSI Approved :: GNU General Public License v3 (GPLv3)
Classifier: Operating System :: POSIX :: Linux
